pyshifty-0.0.6.dist-info/METADATA
pyshifty-0.0.6.dist-info/WHEEL
shifty/__init__.py
shifty/__init__.pyi
shifty/py.typed
shifty/shifty.cpython-313t-darwin.so
pyshifty-0.0.6.dist-info/RECORD
