Metadata-Version: 2.4
Name: pyshifty
Version: 0.0.6
Requires-Dist: maturin>=1.9.6
Requires-Dist: ontoenv>=0.4.0
Requires-Dist: rdflib>=7.4.0
Requires-Dist: sphinx>=7.2 ; extra == 'docs'
Provides-Extra: docs
Summary: Python bindings for the shifty validation engine
Home-Page: https://github.com/gtfierro/shifty
Author-email: Gabe Fierro <gtfierro@mines.edu>
Requires-Python: >=3.11
Project-URL: Repository, https://github.com/gtfierro/shifty
